{"artist":"Flow","name":"Sign","lyrics":[{"startTime":630,"endTime":2150,"text":"I realize the"},{"startTime":2150,"endTime":4140,"text":"screaming pain"},{"startTime":4140,"endTime":6660,"text":"Hearing loud in my brain"},{"startTime":6660,"endTime":9150,"text":"But I'm going straight"},{"startTime":9150,"endTime":15790,"text":"ahead, with the scar"},{"startTime":15790,"endTime":25040,"text":"(Can you hear me So am I)"},{"startTime":25040,"endTime":28760,"text":"Wasurete shimaeba ii yo"},{"startTime":28760,"endTime":31240,"text":"kanji-naku nacchae-ba ii"},{"startTime":31240,"endTime":34010,"text":"Surimuita kokoro ni"},{"startTime":34010,"endTime":35500,"text":"futa o shitanda"},{"startTime":35500,"endTime":39000,"text":"Kizutsuitatte heikidayo"},{"startTime":39000,"endTime":41260,"text":"mou itami wa nai kara ne"},{"startTime":41260,"endTime":45000,"text":"Sono ashi o hikizuri"},{"startTime":45000,"endTime":47260,"text":"nagara mo"},{"startTime":47260,"endTime":48870,"text":"Miushinatta"},{"startTime":48870,"endTime":50000,"text":"Jibun jishin ga"},{"startTime":50000,"endTime":51520,"text":"Oto o tatete"},{"startTime":51520,"endTime":53020,"text":"Kuzureteitta"},{"startTime":53020,"endTime":54900,"text":"Kizukeba kaze no"},{"startTime":54900,"endTime":57530,"text":"oto dake ga"},{"startTime":57530,"endTime":61170,"text":"Tsutaeni kitayo kizuato"},{"startTime":61170,"endTime":63260,"text":"tadotte"},{"startTime":63260,"endTime":67020,"text":"Sekai ni oshitsubusarete"},{"startTime":67020,"endTime":68050,"text":"shimau mae ni"},{"startTime":68050,"endTime":71280,"text":"Oboeterukana namida"},{"startTime":71280,"endTime":73760,"text":"no sora o"},{"startTime":73760,"endTime":76760,"text":"Ano itami ga kimi no"},{"startTime":76760,"endTime":78250,"text":"koto o mamotte kureta"},{"startTime":78250,"endTime":81510,"text":"Sono itami ga itsumo"},{"startTime":81510,"endTime":83520,"text":"kimi o mamotterunda"},{"startTime":83520,"endTime":93520,"text":"(Can you hear me So am I)"}]}